abydos/__init__.py
abydos/version.py
abydos/compression/__init__.py
abydos/compression/_arithmetic.py
abydos/compression/_bwt.py
abydos/compression/_rle.py
abydos/corpus/__init__.py
abydos/corpus/_corpus.py
abydos/corpus/_ngram_corpus.py
abydos/corpus/_unigram_corpus.py
abydos/distance/__init__.py
abydos/distance/_affinegap.py
abydos/distance/_aline.py
abydos/distance/_ample.py
abydos/distance/_anderberg.py
abydos/distance/_andres_marzo_delta.py
abydos/distance/_average_linkage.py
abydos/distance/_azzoo.py
abydos/distance/_bag.py
abydos/distance/_baroni_urbani_buser_i.py
abydos/distance/_baroni_urbani_buser_ii.py
abydos/distance/_batagelj_bren.py
abydos/distance/_baulieu_i.py
abydos/distance/_baulieu_ii.py
abydos/distance/_baulieu_iii.py
abydos/distance/_baulieu_iv.py
abydos/distance/_baulieu_ix.py
abydos/distance/_baulieu_v.py
abydos/distance/_baulieu_vi.py
abydos/distance/_baulieu_vii.py
abydos/distance/_baulieu_viii.py
abydos/distance/_baulieu_x.py
abydos/distance/_baulieu_xi.py
abydos/distance/_baulieu_xii.py
abydos/distance/_baulieu_xiii.py
abydos/distance/_baulieu_xiv.py
abydos/distance/_baulieu_xv.py
abydos/distance/_baystat.py
abydos/distance/_benini_i.py
abydos/distance/_benini_ii.py
abydos/distance/_bennet.py
abydos/distance/_bhattacharyya.py
abydos/distance/_bisim.py
abydos/distance/_bleu.py
abydos/distance/_block_levenshtein.py
abydos/distance/_brainerd_robinson.py
abydos/distance/_braun_blanquet.py
abydos/distance/_canberra.py
abydos/distance/_cao.py
abydos/distance/_chao_dice.py
abydos/distance/_chao_jaccard.py
abydos/distance/_chebyshev.py
abydos/distance/_chord.py
abydos/distance/_clark.py
abydos/distance/_clement.py
abydos/distance/_cohen_kappa.py
abydos/distance/_cole.py
abydos/distance/_complete_linkage.py
abydos/distance/_consonni_todeschini_i.py
abydos/distance/_consonni_todeschini_ii.py
abydos/distance/_consonni_todeschini_iii.py
abydos/distance/_consonni_todeschini_iv.py
abydos/distance/_consonni_todeschini_v.py
abydos/distance/_cormode_lz.py
aj_abydos_mod-0.6.3.dist-info/AUTHORS.rst
aj_abydos_mod-0.6.3.dist-info/LICENSE
aj_abydos_mod-0.6.3.dist-info/METADATA
aj_abydos_mod-0.6.3.dist-info/WHEEL
aj_abydos_mod-0.6.3.dist-info/top_level.txt
aj_abydos_mod-0.6.3.dist-info/RECORD
