Metadata-Version: 2.1
Name: aj-abydos-mod
Version: 0.6.3
Summary: Fork of the Abydos NLP/IR library
Home-page: https://github.com/anuj1508/abydos
Download-URL: https://github.com/anuj1508/abydos/archive/master.zip
Author: Christopher C. Little
Author-email: chrisclittle+abydos@gmail.com
License: GPLv3+
Keywords: nlp,ai,ir,language,linguistics,phonetic algorithms,string distance
Classifier: Programming Language :: Python
Classifier: Programming Language :: Python :: 3
Classifier: Programming Language :: Python :: 3.8
Classifier: Programming Language :: Python :: 3.9
Classifier: Development Status :: 5 - Production/Stable
Classifier: Intended Audience :: Developers
Classifier: License :: OSI Approved :: GNU General Public License v3 or later (GPLv3+)
Classifier: Operating System :: OS Independent
Classifier: Topic :: Scientific/Engineering :: Artificial Intelligence
Classifier: Topic :: Software Development :: Libraries :: Python Modules
Classifier: Topic :: Text Processing :: Indexing
Classifier: Topic :: Text Processing :: Linguistic
Classifier: Natural Language :: English
Requires-Python: >=3.8
License-File: LICENSE
License-File: AUTHORS.rst
Requires-Dist: numpy
Requires-Dist: Cython <=0.29.36,>=0.29.14
Provides-Extra: all
Requires-Dist: paq ; extra == 'all'
Requires-Dist: sphinxcontrib-bibtex ; extra == 'all'
Requires-Dist: Cython <=0.29.36,>=0.29.14 ; extra == 'all'
Requires-Dist: lzss ; extra == 'all'
Requires-Dist: sphinx-rtd-theme ; extra == 'all'
Requires-Dist: syllabipy ; extra == 'all'
Requires-Dist: nltk ; extra == 'all'
Requires-Dist: twine ; extra == 'all'
Requires-Dist: deprecation ; extra == 'all'
Requires-Dist: wheel ; extra == 'all'
Requires-Dist: numpy ; extra == 'all'
Provides-Extra: dev
Requires-Dist: paq ; extra == 'dev'
Requires-Dist: sphinxcontrib-bibtex ; extra == 'dev'
Requires-Dist: Cython <=0.29.36,>=0.29.14 ; extra == 'dev'
Requires-Dist: lzss ; extra == 'dev'
Requires-Dist: sphinx-rtd-theme ; extra == 'dev'
Requires-Dist: syllabipy ; extra == 'dev'
Requires-Dist: twine ; extra == 'dev'
Requires-Dist: nltk ; extra == 'dev'
Requires-Dist: deprecation ; extra == 'dev'
Requires-Dist: numpy ; extra == 'dev'
Requires-Dist: wheel ; extra == 'dev'
Provides-Extra: test
Requires-Dist: paq ; extra == 'test'
Requires-Dist: Cython <=0.29.36,>=0.29.14 ; extra == 'test'
Requires-Dist: lzss ; extra == 'test'
Requires-Dist: syllabipy ; extra == 'test'
Requires-Dist: nltk ; extra == 'test'
Requires-Dist: numpy ; extra == 'test'
